comicfn2dict/__init__.py
comicfn2dict/cli.py
comicfn2dict/log.py
comicfn2dict/parse.py
comicfn2dict/regex.py
comicfn2dict/unparse.py
comicfn2dict-0.2.4.dist-info/LICENSE
comicfn2dict-0.2.4.dist-info/METADATA
comicfn2dict-0.2.4.dist-info/WHEEL
comicfn2dict-0.2.4.dist-info/entry_points.txt
comicfn2dict-0.2.4.dist-info/RECORD
